Metadata-Version: 2.1
Name: humanai
Version: 1.0.0
Summary: Turns common questions into human responses.
Home-page: UNKNOWN
Author: Me
License: MIT
Platform: UNKNOWN
